fast_dict/__init__.py
fast_dict/core.py
fast_dict-1.0.6.dist-info/METADATA
fast_dict-1.0.6.dist-info/WHEEL
fast_dict-1.0.6.dist-info/top_level.txt
fast_dict-1.0.6.dist-info/zip-safe
fast_dict-1.0.6.dist-info/RECORD
