Metadata-Version: 2.1
Name: fast-dict
Version: 1.0.6
Summary: A class that operates quickly on dict
Home-page: UNKNOWN
Author: _凌川
Author-email: 2282440078@qq.com
License: UNKNOWN
Platform: UNKNOWN
Classifier: License :: OSI Approved :: MIT License
Classifier: Programming Language :: Python
Classifier: Programming Language :: Python :: 3.8
Requires-Dist: jsonpath (>=0.82)
